lakefs_client/__init__.py
lakefs_client/api_client.py
lakefs_client/client.py
lakefs_client/configuration.py
lakefs_client/exceptions.py
lakefs_client/model_utils.py
lakefs_client/rest.py
lakefs_client/api/__init__.py
lakefs_client/api/actions_api.py
lakefs_client/api/auth_api.py
lakefs_client/api/branches_api.py
lakefs_client/api/commits_api.py
lakefs_client/api/config_api.py
lakefs_client/api/experimental_api.py
lakefs_client/api/external_api.py
lakefs_client/api/health_check_api.py
lakefs_client/api/import_api.py
lakefs_client/api/internal_api.py
lakefs_client/api/metadata_api.py
lakefs_client/api/objects_api.py
lakefs_client/api/pulls_api.py
lakefs_client/api/refs_api.py
lakefs_client/api/repositories_api.py
lakefs_client/api/staging_api.py
lakefs_client/api/tags_api.py
lakefs_client/apis/__init__.py
lakefs_client/model/__init__.py
lakefs_client/model/abort_presign_multipart_upload.py
lakefs_client/model/access_key_credentials.py
lakefs_client/model/acl.py
lakefs_client/model/action_run.py
lakefs_client/model/action_run_list.py
lakefs_client/model/auth_capabilities.py
lakefs_client/model/authentication_token.py
lakefs_client/model/branch_creation.py
lakefs_client/model/branch_protection_rule.py
lakefs_client/model/cherry_pick_creation.py
lakefs_client/model/comm_prefs_input.py
lakefs_client/model/commit.py
lakefs_client/model/commit_creation.py
lakefs_client/model/commit_list.py
lakefs_client/model/commit_overrides.py
lakefs_client/model/commit_record_creation.py
lakefs_client/model/complete_presign_multipart_upload.py
lakefs_client/model/config.py
lakefs_client/model/credentials.py
lakefs_client/model/credentials_list.py
lakefs_client/model/credentials_with_secret.py
lakefs_client/model/current_user.py
lakefs_client/model/diff.py
lakefs_client/model/diff_list.py
lakefs_client/model/error.py
lakefs_client/model/error_no_acl.py
lakefs_client/model/external_login_information.py
lakefs_client/model/external_principal.py
lakefs_client-1.44.0.dist-info/METADATA
lakefs_client-1.44.0.dist-info/WHEEL
lakefs_client-1.44.0.dist-info/top_level.txt
lakefs_client-1.44.0.dist-info/RECORD
