Metadata-Version: 2.1
Name: lakefs-client
Version: 1.44.0
Summary: [legacy] lakeFS API
Home-page: https://github.com/treeverse/lakeFS/tree/master/clients/python-legacy
Author: Treeverse
Author-email: services@treeverse.io
License: Apache 2.0
Keywords: OpenAPI,OpenAPI-Generator,lakeFS API
Requires-Python: >=3.6
Requires-Dist: urllib3>=1.25.3
Requires-Dist: python-dateutil
